tokenledger/__init__.py
tokenledger/alembic.ini
tokenledger/async_db.py
tokenledger/config.py
tokenledger/context.py
tokenledger/decorators.py
tokenledger/middleware.py
tokenledger/models.py
tokenledger/pricing.py
tokenledger/py.typed
tokenledger/queries.py
tokenledger/server.py
tokenledger/tracker.py
tokenledger/alembic/env.py
tokenledger/alembic/script.py.mako
tokenledger/alembic/versions/20240101_0000_001_initial_schema.py
tokenledger/alembic/versions/20240201_0000_002_attribution_fields.py
tokenledger/backends/__init__.py
tokenledger/backends/base.py
tokenledger/backends/exceptions.py
tokenledger/backends/protocol.py
tokenledger/backends/registry.py
tokenledger/backends/postgresql/__init__.py
tokenledger/backends/postgresql/async_storage.py
tokenledger/backends/postgresql/schema.py
tokenledger/backends/postgresql/storage.py
tokenledger/cli/__init__.py
tokenledger/cli/db.py
tokenledger/interceptors/__init__.py
tokenledger/interceptors/anthropic.py
tokenledger/interceptors/google.py
tokenledger/interceptors/openai.py
tokenledger/migrations/__init__.py
tokenledger/migrations/runner.py
tokenledger-0.1.1.dist-info/METADATA
tokenledger-0.1.1.dist-info/WHEEL
tokenledger-0.1.1.dist-info/entry_points.txt
tokenledger-0.1.1.dist-info/licenses/LICENSE
tokenledger-0.1.1.dist-info/RECORD
