Metadata-Version: 2.4
Name: tokenledger
Version: 0.1.1
Summary: LLM Cost Analytics for Postgres - Know exactly what your AI features cost
Project-URL: Homepage, https://github.com/ged1182/tokenledger
Project-URL: Documentation, https://github.com/ged1182/tokenledger#readme
Project-URL: Repository, https://github.com/ged1182/tokenledger
Project-URL: Issues, https://github.com/ged1182/tokenledger/issues
Project-URL: Changelog, https://github.com/ged1182/tokenledger/blob/main/CHANGELOG.md
Author-email: George Dekermenjian <ged118@gmail.com>
Maintainer-email: George Dekermenjian <ged118@gmail.com>
License: Elastic-2.0
License-File: LICENSE
Keywords: ai,analytics,anthropic,claude,cost,gpt,llm,observability,openai,postgres
Classifier: Development Status :: 4 - Beta
Classifier: Intended Audience :: Developers
Classifier: License :: Other/Proprietary License
Classifier: Operating System :: OS Independent
Classifier: Programming Language :: Python :: 3
Classifier: Programming Language :: Python :: 3.11
Classifier: Programming Language :: Python :: 3.12
Classifier: Programming Language :: Python :: 3.13
Classifier: Topic :: Software Development :: Libraries :: Python Modules
Classifier: Topic :: System :: Monitoring
Classifier: Typing :: Typed
Requires-Python: >=3.11
Requires-Dist: alembic>=1.18.1
Requires-Dist: psycopg2-binary>=2.9.11
Requires-Dist: pydantic<3,>=2.0.0
Requires-Dist: rich>=13.0.0
Requires-Dist: typer>=0.9.0
Provides-Extra: all
Requires-Dist: anthropic>=0.18.0; extra == 'all'
Requires-Dist: asyncpg>=0.29.0; extra == 'all'
Requires-Dist: fastapi>=0.104.0; extra == 'all'
Requires-Dist: google-genai>=1.0.0; extra == 'all'
Requires-Dist: openai>=1.0.0; extra == 'all'
Requires-Dist: uvicorn[standard]>=0.24.0; extra == 'all'
Provides-Extra: anthropic
Requires-Dist: anthropic>=0.18.0; extra == 'anthropic'
Provides-Extra: asyncpg
Requires-Dist: asyncpg>=0.29.0; extra == 'asyncpg'
Provides-Extra: dev
Requires-Dist: mypy>=1.13.0; extra == 'dev'
Requires-Dist: pre-commit>=3.5.0; extra == 'dev'
Requires-Dist: pytest-asyncio>=0.23.0; extra == 'dev'
Requires-Dist: pytest-cov>=4.0.0; extra == 'dev'
Requires-Dist: pytest>=8.0.0; extra == 'dev'
Requires-Dist: ruff>=0.8.0; extra == 'dev'
Provides-Extra: google
Requires-Dist: google-genai>=1.0.0; extra == 'google'
Provides-Extra: openai
Requires-Dist: openai>=1.0.0; extra == 'openai'
Provides-Extra: server
Requires-Dist: fastapi>=0.104.0; extra == 'server'
Requires-Dist: uvicorn[standard]>=0.24.0; extra == 'server'
Provides-Extra: server-async
Requires-Dist: asyncpg>=0.29.0; extra == 'server-async'
Requires-Dist: fastapi>=0.104.0; extra == 'server-async'
Requires-Dist: uvicorn[standard]>=0.24.0; extra == 'server-async'
